{
  "$schema": "../gen/schemas/desktop-schema.json",
  "identifier": "main-capability",
  "description": "Permissions used by the Rust Meow main window",
  "windows": ["main"],
  "permissions": [
    "core:default",
    "dialog:allow-open",
    "notification:default",
    "opener:allow-open-url",
    "opener:allow-default-urls",
    "core:window:allow-start-dragging",
    "core:window:allow-start-resize-dragging",
    "core:window:allow-minimize",
    "core:window:allow-toggle-maximize",
    "core:window:allow-close",
    "core:window:allow-is-maximized"
  ]
}
